LymphoMNIST/LymphoMNIST.py
LymphoMNIST/__init__.py
LymphoMNIST/info.py
LymphoMNIST/utils.py
lymphomnist-1.0.dist-info/licenses/LICENSE
tests/__init__.py
tests/test_lymphomnist.py
lymphomnist-1.0.dist-info/METADATA
lymphomnist-1.0.dist-info/WHEEL
lymphomnist-1.0.dist-info/top_level.txt
lymphomnist-1.0.dist-info/RECORD
