Metadata-Version: 2.4
Name: LymphoMNIST
Version: 1.0
Summary: A comprehensive dataset for lymphocyte image classification (B cells, T4 cells, and T8 cells).
Home-page: https://github.com/Khayrulbuet13/LymphoMNIST
Author: Khayrul Islam
Author-email: Khayrul Islam <khayrulbuet13@alum.lehigh.edu>
License:                                  Apache License
Project-URL: Homepage, https://github.com/Khayrulbuet13/LymphoMNIST
Project-URL: Bug Reports, https://github.com/Khayrulbuet13/LymphoMNIST/issues
Project-URL: Source, https://github.com/Khayrulbuet13/LymphoMNIST
Project-URL: Documentation, https://github.com/Khayrulbuet13/LymphoMNIST/blob/main/README.md
Keywords: pytorch,dataset,lymphocyte,classification,CNN,MNIST,biomedical,imaging,machine-learning
Classifier: Development Status :: 5 - Production/Stable
Classifier: Intended Audience :: Developers
Classifier: Intended Audience :: Science/Research
Classifier: Programming Language :: Python :: 3
Classifier: Programming Language :: Python :: 3.6
Classifier: Programming Language :: Python :: 3.7
Classifier: Programming Language :: Python :: 3.8
Classifier: Programming Language :: Python :: 3.9
Classifier: Programming Language :: Python :: 3.10
Classifier: License :: OSI Approved :: Apache Software License
Classifier: Operating System :: OS Independent
Classifier: Topic :: Scientific/Engineering :: Artificial Intelligence
Classifier: Topic :: Scientific/Engineering :: Image Recognition
Classifier: Topic :: Scientific/Engineering :: Medical Science Apps.
Requires-Python: >=3.6
License-File: LICENSE
Requires-Dist: torch
Requires-Dist: torchvision
Requires-Dist: matplotlib
Requires-Dist: numpy
Requires-Dist: Pillow
Requires-Dist: tqdm
Requires-Dist: requests
Dynamic: author
Dynamic: home-page
Dynamic: license-file
Dynamic: requires-python
